py_testbed/__init__.py
py_testbed/py_testbed.py
py_testbed-0.0.1.dist-info/LICENSE
py_testbed-0.0.1.dist-info/METADATA
py_testbed-0.0.1.dist-info/WHEEL
py_testbed-0.0.1.dist-info/top_level.txt
py_testbed-0.0.1.dist-info/RECORD
