Metadata-Version: 2.1
Name: py-testbed
Version: 0.0.1
Summary: Python library to run a battery of scripts for e.g code testing
Author-email: Purple Elephant <purple.elephant1037@gmail.com>
Project-URL: Homepage, https://github.com/purple-elephant1037/py_testbed
Project-URL: Test code, https://github.com/purple-elephant1037/py_testbed
Classifier: Programming Language :: Python :: 3
Classifier: License :: OSI Approved :: MIT License
Classifier: Operating System :: OS Independent
Classifier: Topic :: Utilities
Requires-Python: >=3.7
License-File: LICENSE
